zephyr_sdk/__init__.py
zephyr_sdk/zephyr.py
zephyr_sdk/components/__init__.py
zephyr_sdk/components/cycles.py
zephyr_sdk/components/defects.py
zephyr_sdk/components/projects.py
zephyr_sdk/components/releases.py
zephyr_sdk/components/requirements.py
zephyr_sdk/components/requirementtrees.py
zephyr_sdk/components/testcases.py
zephyr_sdk/components/testcasetrees.py
zephyr_sdk/components/users.py
zephyr_sdk/enumerations/__init__.py
zephyr_sdk/enumerations/defects.py
zephyr_sdk/exceptions/ZExceptions.py
zephyr_sdk/exceptions/__init__.py
zephyr_sdk-0.2.1.dist-info/LICENSE
zephyr_sdk-0.2.1.dist-info/METADATA
zephyr_sdk-0.2.1.dist-info/WHEEL
zephyr_sdk-0.2.1.dist-info/top_level.txt
zephyr_sdk-0.2.1.dist-info/RECORD
