Metadata-Version: 2.1
Name: zephyr-sdk
Version: 0.2.1
Summary: A package for helping use the zephyr API
Home-page: https://github.com/byu-oit/zephyr-sdk
Author: Mark Roth
Author-email: mark_roth@byu.edu
License: UNKNOWN
Platform: UNKNOWN
Classifier: Programming Language :: Python :: 3
Classifier: License :: OSI Approved :: Apache Software License 
Classifier: Operating System :: OS Independent
Requires-Python: >=3.8
Requires-Dist: requests (<3.0.0,>=2.23.0)
